pyreflat/__init__.py
pyreflat/any_path_writer.py
pyreflat/conv.py
pyreflat/core.py
pyreflat/flatter.py
pyreflat/interp.py
pyreflat/tab_flat.py
pyreflat/terminal_writer.py
pyreflat/tokens.py
pyreflat/util.py
pyreflat-0.0.5.dist-info/LICENSE.md
pyreflat-0.0.5.dist-info/METADATA
pyreflat-0.0.5.dist-info/WHEEL
pyreflat-0.0.5.dist-info/top_level.txt
pyreflat-0.0.5.dist-info/RECORD
