Metadata-Version: 2.1
Name: pyreflat
Version: 0.0.5
Summary: pyreflat - flatten python dict or json
Home-page: https://github.com/kr-g/pyreflat
Author: k.r. goger
Author-email: k.r.goger+pyreflat@gmail.com
License: UNKNOWN
Keywords: python flatten dict json serialize serialization persitence config pickel
Platform: UNKNOWN
Classifier: Development Status :: 3 - Alpha
Classifier: Operating System :: POSIX :: Linux
Classifier: Intended Audience :: Developers
Classifier: Programming Language :: Python :: 3
Classifier: License :: OSI Approved :: GNU Affero General Public License v3 or later (AGPLv3+)
Requires-Python: >=3.6
